{
  "service": {
    "service": "new-service",
    "serviceObject": {
      "name": "new-service"
    },
    "provider": {
      "name": "aws",
      "stage": "dev",
      "variableSyntax": "\\${([^{}:]+?(?:\\(|:)(?:[^:{}][^{}]*?)?)}",
      "region": "us-east-1",
      "versionFunctions": true,
      "compiledCloudFormationTemplate": {
        "AWSTemplateFormatVersion": "2010-09-09",
        "Description": "The AWS CloudFormation template for this Serverless application",
        "Resources": {
          "ServerlessDeploymentBucket": {
            "Type": "AWS::S3::Bucket",
            "Properties": {
              "BucketEncryption": {
                "ServerSideEncryptionConfiguration": [
                  {
                    "ServerSideEncryptionByDefault": {
                      "SSEAlgorithm": "AES256"
                    }
                  }
                ]
              }
            }
          },
          "ServerlessDeploymentBucketPolicy": {
            "Type": "AWS::S3::BucketPolicy",
            "Properties": {
              "Bucket": {
                "Ref": "ServerlessDeploymentBucket"
              },
              "PolicyDocument": {
                "Statement": [
                  {
                    "Action": "s3:*",
                    "Effect": "Deny",
                    "Principal": "*",
                    "Resource": [
                      {
                        "Fn::Join": [
                          "",
                          [
                            "arn:",
                            {
                              "Ref": "AWS::Partition"
                            },
                            ":s3:::",
                            {
                              "Ref": "ServerlessDeploymentBucket"
                            },
                            "/*"
                          ]
                        ]
                      },
                      {
                        "Fn::Join": [
                          "",
                          [
                            "arn:",
                            {
                              "Ref": "AWS::Partition"
                            },
                            ":s3:::",
                            {
                              "Ref": "ServerlessDeploymentBucket"
                            }
                          ]
                        ]
                      }
                    ],
                    "Condition": {
                      "Bool": {
                        "aws:SecureTransport": false
                      }
                    }
                  }
                ]
              }
            }
          }
        },
        "Outputs": {
          "ServerlessDeploymentBucketName": {
            "Value": {
              "Ref": "ServerlessDeploymentBucket"
            }
          }
        }
      },
      "coreCloudFormationTemplate": {
        "AWSTemplateFormatVersion": "2010-09-09",
        "Description": "The AWS CloudFormation template for this Serverless application",
        "Resources": {
          "ServerlessDeploymentBucket": {
            "Type": "AWS::S3::Bucket",
            "Properties": {
              "BucketEncryption": {
                "ServerSideEncryptionConfiguration": [
                  {
                    "ServerSideEncryptionByDefault": {
                      "SSEAlgorithm": "AES256"
                    }
                  }
                ]
              }
            }
          },
          "ServerlessDeploymentBucketPolicy": {
            "Type": "AWS::S3::BucketPolicy",
            "Properties": {
              "Bucket": {
                "Ref": "ServerlessDeploymentBucket"
              },
              "PolicyDocument": {
                "Statement": [
                  {
                    "Action": "s3:*",
                    "Effect": "Deny",
                    "Principal": "*",
                    "Resource": [
                      {
                        "Fn::Join": [
                          "",
                          [
                            "arn:",
                            {
                              "Ref": "AWS::Partition"
                            },
                            ":s3:::",
                            {
                              "Ref": "ServerlessDeploymentBucket"
                            },
                            "/*"
                          ]
                        ]
                      },
                      {
                        "Fn::Join": [
                          "",
                          [
                            "arn:",
                            {
                              "Ref": "AWS::Partition"
                            },
                            ":s3:::",
                            {
                              "Ref": "ServerlessDeploymentBucket"
                            }
                          ]
                        ]
                      }
                    ],
                    "Condition": {
                      "Bool": {
                        "aws:SecureTransport": false
                      }
                    }
                  }
                ]
              }
            }
          }
        },
        "Outputs": {
          "ServerlessDeploymentBucketName": {
            "Value": {
              "Ref": "ServerlessDeploymentBucket"
            }
          }
        }
      }
    },
    "pluginsData": {},
    "functions": {},
    "configValidationMode": "warn",
    "serviceFilename": "serverless.yml",
    "layers": {},
    "initialServerlessConfig": {
      "name": "clink-homepage",
      "service": {
        "$ref": "$[\"service\"][\"serviceObject\"]"
      },
      "provider": {
        "$ref": "$[\"service\"][\"provider\"]"
      },
      "clink-homepage": {
        "--component": "serverless-next.js@latest",
        "inputs": {
          "bucketName": "clink-homepage-s3",
          "description": "clink-homepage-serverless-deploy",
          "name": {
            "defaultLambda": "clink-homepage-lambda",
            "apiLambda": "clink-hoempage-lambda"
          },
          "domain": [
            "clink-homepage",
            "cauclink.com"
          ],
          "runtime": {
            "defaultLambda": "nodejs12.x",
            "apiLambda": "nodejs12.x"
          },
          "custom": {
            "customDomain": {
              "domainName": "hello.cauclink.com",
              "basePath": "",
              "certificateName": "*.cauclink.com",
              "createRoute53Record": true
            }
          }
        }
      }
    },
    "isDashboardMonitoringPreconfigured": false
  },
  "package": {
    "artifactDirectoryName": "serverless/new-service/dev/1612702336317-2021-02-07T12:52:16.317Z",
    "artifact": ""
  }
}